.bumpversion.cfg
.cookiecutterrc
.coveragerc
.editorconfig
AUTHORS.rst
CHANGELOG.rst
CONTRIBUTING.rst
LICENSE
MANIFEST.in
README.rst
setup.cfg
setup.py
tox.ini
ci/bootstrap.py
docs/authors.rst
docs/changelog.rst
docs/conf.py
docs/contributing.rst
docs/index.rst
docs/installation.rst
docs/readme.rst
docs/requirements.txt
docs/spelling_wordlist.txt
docs/usage.rst
docs/reference/index.rst
docs/reference/thundercache.rst
src/thundercache/__init__.py
src/thundercache/base.py
src/thundercache.egg-info/PKG-INFO
src/thundercache.egg-info/SOURCES.txt
src/thundercache.egg-info/dependency_links.txt
src/thundercache.egg-info/not-zip-safe
src/thundercache.egg-info/top_level.txt
tests/test_thundercache.py